ifc2osmod/__init__.py
ifc2osmod/add_sch2osmod.py
ifc2osmod/calc_massless_mat.py
ifc2osmod/epsql2csv.py
ifc2osmod/execute_osmod.py
ifc2osmod/extract_osmod_opq_constr.py
ifc2osmod/extract_osmod_smpl_glz_constr.py
ifc2osmod/freecad_custom_pset.py
ifc2osmod/idf2osmod.py
ifc2osmod/idf_transition.py
ifc2osmod/ifcarch2osmod.py
ifc2osmod/osmod2ifcarch.py
ifc2osmod/read_ifc_envlp_mat_pset.py
ifc2osmod/read_ifc_mat_pset.py
ifc2osmod/settings.py
ifc2osmod/data/json/mea_sel_schema.json
ifc2osmod/data/json/ashrae90_1/ashrae_90_1.climate_zone_sets.json
ifc2osmod/data/json/ashrae90_1/ashrae_90_1.climate_zones.json
ifc2osmod/data/json/ashrae90_1/ashrae_90_1.fans.json
ifc2osmod/data/json/ashrae90_1/ashrae_90_1.schedules.json
ifc2osmod/data/json/ashrae90_1/ashrae_90_1_prm.curves.json
ifc2osmod/data/json/ifc_psets/osmod_material_schema.json
ifc2osmod/data/json/ifc_psets/osmod_nomass_schema.json
ifc2osmod/data/json/ifc_psets/osmod_simple_glazing_schema.json
ifc2osmod/data/json/ifc_psets/osmod_space_schema.json
ifc2osmod/data/json/ifc_psets/osmod_spacetype_schema.json
ifc2osmod/data/json/ifc_psets/osmod_std_opq_material_schema.json
ifc2osmod/data/json/ifc_psets/osmod_thermal_resistance_schema.json
ifc2osmod/data/json/ifc_psets/osmod_ufactor_schema.json
ifc2osmod/data/json/osmod_data/osmod_opq_constr_info.json
ifc2osmod/data/json/osmod_data/osmod_opq_smplglz_constr_schema.json
ifc2osmod/data/json/osmod_data/osmod_smpl_glz_constr_info.json
ifc2osmod/utils/openstudio_utils.py
ifc2osmod/utils/utils.py
ifc2osmod-0.0.7.dist-info/LICENSE
ifc2osmod-0.0.7.dist-info/METADATA
ifc2osmod-0.0.7.dist-info/WHEEL
ifc2osmod-0.0.7.dist-info/entry_points.txt
ifc2osmod-0.0.7.dist-info/top_level.txt
ifc2osmod-0.0.7.dist-info/RECORD
