Metadata-Version: 2.2
Name: ifc2osmod
Version: 0.0.7
Summary: Python-based command line tool for converting IFC files to Openstudio models
Author-email: Kian Wee CHEN <chenkianwee@gmail.com>
Project-URL: Homepage, https://github.com/chenkianwee/ifc2osmod
Project-URL: Bug Tracker, https://github.com/chenkianwee/ifc2osmod/issues
Classifier: License :: OSI Approved :: GNU General Public License v3 (GPLv3)
Classifier: Programming Language :: Python :: 3.10
Classifier: Operating System :: OS Independent
Requires-Python: <3.13,>=3.10
License-File: LICENSE
Requires-Dist: ifc_utils==0.0.5
Requires-Dist: openstudio==3.8.0
Requires-Dist: ladybug-core==0.43.22
Requires-Dist: setuptools==75.8.0
Provides-Extra: viewer3d
Requires-Dist: ifc_utils[viewer3d]==0.0.5; extra == "viewer3d"
